yuanbian_utils/__init__.py
yuanbian_utils/docx.py
yuanbian_utils/xlsx.py
yuanbian_utils-0.2.dist-info/METADATA
yuanbian_utils-0.2.dist-info/WHEEL
yuanbian_utils-0.2.dist-info/top_level.txt
yuanbian_utils-0.2.dist-info/RECORD
