Metadata-Version: 2.1
Name: yuanbian-utils
Version: 0.2
Summary: 用于猿变实验室的工具库
Home-page: https://python-xp.com
Author: yuanbian-lab
Author-email: luxp4588@126.com
License: MIT
Keywords: yuanbian utils
Platform: any
Classifier: Development Status :: 5 - Production/Stable
Classifier: Environment :: Web Environment
Classifier: Intended Audience :: Developers
Classifier: License :: OSI Approved :: MIT License
Classifier: Programming Language :: Python :: 3.7
Classifier: Programming Language :: Python :: 3.8
Classifier: Programming Language :: Python :: 3.9
Classifier: Topic :: Internet :: WWW/HTTP :: Dynamic Content
Classifier: Topic :: Software Development :: Libraries :: Python Modules
Requires-Dist: ipython
Requires-Dist: mammoth
